metocean_api/__init__.py
metocean_api/ts/__init__.py
metocean_api/ts/ts_mod.py
metocean_api/ts/internal/__init__.py
metocean_api/ts/internal/aux_funcs.py
metocean_api/ts/internal/convention.py
metocean_api/ts/internal/product.py
metocean_api/ts/internal/products.py
metocean_api/ts/internal/ec/__init__.py
metocean_api/ts/internal/ec/ec_products.py
metocean_api/ts/internal/metno/__init__.py
metocean_api/ts/internal/metno/met_product.py
metocean_api/ts/internal/metno/met_products.py
metocean_api/ts/internal/tudelft/__init__.py
metocean_api/ts/internal/tudelft/tudelft_products.py
tests/__init__.py
tests/test_combine_data.py
tests/test_extract_data.py
tests/data/NORA3_atm_sub_lon1.32_lat53.324_20210101_20210331.csv
tests/data/NORA3_wind_sub_lon1.32_lat53.324_20210101_20210131.csv
metocean_api-1.1.10.dist-info/LICENSE
metocean_api-1.1.10.dist-info/METADATA
metocean_api-1.1.10.dist-info/WHEEL
metocean_api-1.1.10.dist-info/top_level.txt
metocean_api-1.1.10.dist-info/RECORD
