Metadata-Version: 2.1
Name: metocean-api
Version: 1.1.10
Summary: metocean-api - Tool to extract time series of metocean data from hindcasts/reanalysis
Home-page: https://github.com/MET-OM/metocean-api
Download-URL: https://github.com/MET-OM/metocean-api
Author: Konstantinos Christakos MET Norway & NTNU
License: LGPLv2.1
License-File: LICENSE
Requires-Dist: matplotlib >=3.1
Requires-Dist: numpy >=1.17
Requires-Dist: pandas
Requires-Dist: xarray
Requires-Dist: dask
Requires-Dist: pip
Requires-Dist: netcdf4
Requires-Dist: cartopy
